xemc3/__init__.py
xemc3/_version.py
xemc3/config.py
xemc3/cli/__init__.py
xemc3/cli/_common.py
xemc3/cli/append_time.py
xemc3/cli/to_archive.py
xemc3/cli/to_netcdf.py
xemc3/cli/xdivertor.py
xemc3/core/__init__.py
xemc3/core/config.py
xemc3/core/dataset.py
xemc3/core/depo.py
xemc3/core/evaluate_at.py
xemc3/core/load.py
xemc3/core/plot_2d.py
xemc3/core/plot_3d.py
xemc3/core/utils.py
xemc3/data/default.yaml
xemc3/data/v0.2.0.yaml
xemc3/data/v0.2.1.yaml
xemc3/data/v0.2.2.yaml
xemc3/data/v0.2.3.yaml
xemc3/data/v0.2.4.yaml
xemc3/data/v0.2.5.yaml
xemc3/data/v0.2.6.yaml
xemc3/data/v1.0.0.yaml
xemc3/load/__init__.py
xemc3/test/__init__.py
xemc3/test/gen_ds.py
xemc3/test/test_average.py
xemc3/test/test_basic.py
xemc3/test/test_cli.py
xemc3/test/test_dataset.py
xemc3/test/test_load_real.py
xemc3/test/test_utils.py
xemc3/test/test_write_load.py
xemc3/tools/run_wrapper.py
xemc3/write/__init__.py
xemc3/write/fortran.py
xemc3/write/nc.py
xemc3-1.0.0.dist-info/licenses/COPYING
xemc3-1.0.0.dist-info/METADATA
xemc3-1.0.0.dist-info/WHEEL
xemc3-1.0.0.dist-info/entry_points.txt
xemc3-1.0.0.dist-info/top_level.txt
xemc3-1.0.0.dist-info/RECORD
