Metadata-Version: 2.4
Name: xemc3
Version: 1.0.0
Summary: Collect data from EMC3 runs in python using xarray
Home-page: https://github.com/dschwoerer/xemc3
Author: David Bold
Author-email: dave@ipp.mpg.de
License: GPL
Project-URL: Tracker, https://github.com/dschwoerer/xemc3/issues
Project-URL: Documentation, https://xemc3.rtfd.io
Classifier: Development Status :: 4 - Beta
Classifier: Intended Audience :: Science/Research
Classifier: Intended Audience :: Education
Classifier: Intended Audience :: Developers
Classifier: License :: OSI Approved :: GNU General Public License v3 or later (GPLv3+)
Classifier: Natural Language :: English
Classifier: Operating System :: POSIX :: Linux
Classifier: Programming Language :: Python :: 3.10
Classifier: Programming Language :: Python :: 3.11
Classifier: Programming Language :: Python :: 3.12
Classifier: Programming Language :: Python :: 3.13
Classifier: Topic :: Scientific/Engineering :: Visualization
License-File: COPYING
Requires-Dist: xarray>=0.16.0
Requires-Dist: netcdf4>=1.4.0
Requires-Dist: importlib-metadata; python_version < "3.8"
Requires-Dist: numpy>=1.13.0
Requires-Dist: eudist
Requires-Dist: pyyaml
Provides-Extra: plot
Requires-Dist: matplotlib!=3.3.0,!=3.3.1,!=3.3.2,>=3.1.1; extra == "plot"
Provides-Extra: plot3d
Requires-Dist: mayavi; extra == "plot3d"
Requires-Dist: vtk!=9.0.2,!=9.0.3; extra == "plot3d"
Provides-Extra: docs
Requires-Dist: sphinx>=1.4; extra == "docs"
Requires-Dist: sphinx-argparse-cli; python_version > "3.6" and extra == "docs"
Requires-Dist: nbsphinx>=0.8.6; extra == "docs"
Provides-Extra: full
Requires-Dist: matplotlib!=3.3.0,!=3.3.1,!=3.3.2,>=3.1.1; extra == "full"
Requires-Dist: mayavi; extra == "full"
Requires-Dist: vtk!=9.0.2,!=9.0.3; extra == "full"
Requires-Dist: sphinx>=1.4; extra == "full"
Requires-Dist: sphinx-argparse-cli; python_version > "3.6" and extra == "full"
Requires-Dist: nbsphinx>=0.8.6; extra == "full"
Requires-Dist: numba; extra == "full"
Dynamic: license-file
